Metadata-Version: 2.1
Name: aserti3416cpp
Version: 0.1.2
Summary: ASERT i3 416 C++ wrapper
Home-page: https://github.com/fpelliccioni
Author: Fernando Pelliccioni
Author-email: fpelliccioni@gmail.com
License: MIT
Keywords: bitcoin cash difficulty daa asert
Platform: UNKNOWN
Classifier: Development Status :: 3 - Alpha
Classifier: Intended Audience :: Developers
Classifier: Topic :: Software Development :: Build Tools
Classifier: License :: OSI Approved :: MIT License
Classifier: Programming Language :: C++
Classifier: Programming Language :: Python :: 2
Classifier: Programming Language :: Python :: 2.7
Classifier: Programming Language :: Python :: 3
Classifier: Programming Language :: Python :: 3.4
Classifier: Programming Language :: Python :: 3.5
Classifier: Programming Language :: Python :: 3.6
Classifier: Programming Language :: Python :: 3.7
Classifier: Programming Language :: Python :: 3.8
Provides-Extra: dev
Provides-Extra: test
